__init__.py
config.py
download.py
main.py
make_file.py
play.py
version.py
errors/__init__.py
errors/auth.py
errors/files.py
errors/shared.py
tts/__init__.py
tts/config.py
tts/download.py
tts/main.py
tts/make_file.py
tts/play.py
tts/errors/__init__.py
tts/errors/auth.py
tts/errors/files.py
tts/errors/shared.py
tts/utils/__init__.py
tts/utils/log.py
utils/__init__.py
utils/log.py
dvtwebapi_py-1.0.3.dist-info/METADATA
dvtwebapi_py-1.0.3.dist-info/WHEEL
dvtwebapi_py-1.0.3.dist-info/top_level.txt
dvtwebapi_py-1.0.3.dist-info/RECORD
