Metadata-Version: 2.2
Name: dvtwebapi.py
Version: 1.0.3
Summary: voicetext web apiをdiscord bot用に使いやすくしたラッパー
Project-URL: homepage, https://github.com/furimu1234/discord_tts_library
Project-URL: repository, https://github.com/furimu1234/discord_tts_library
Requires-Python: >=3.13
Requires-Dist: discord-py
Requires-Dist: parameterized>=0.9.0
Requires-Dist: pytest>=8.3.4
